MANIFEST.in
README.md
setup.cfg
setup.py
mod_ansible_autodoc/__init__.py
mod_ansible_autodoc/commands.py
mod_ansible_autodoc.egg-info/PKG-INFO
mod_ansible_autodoc.egg-info/SOURCES.txt
mod_ansible_autodoc.egg-info/dependency_links.txt
mod_ansible_autodoc.egg-info/entry_points.txt
mod_ansible_autodoc.egg-info/requires.txt
mod_ansible_autodoc.egg-info/top_level.txt
mod_ansible_autodoc/args/__init__.py
mod_ansible_autodoc/args/args.py
mod_ansible_autodoc/files/__init__.py
mod_ansible_autodoc/files/common.py
mod_ansible_autodoc/markdown/__init__.py
mod_ansible_autodoc/markdown/format.py
mod_ansible_autodoc/markdown/parse.py
mod_ansible_autodoc/markdown/todo.py