Metadata-Version: 1.1
Name: mod-ansible-autodoc
Version: 0.5.5
Summary: A wrapper for ansible-autodoc with formatted documentation
Home-page: https://github.com/rennym19/mod-ansible-autodoc
Author: Renny Montero
Author-email: rennym19@gmail.com
License: MIT
Download-URL: https://github.com/rennym19/mod-ansible-autodoc/archive/v_0_5_5.tar.gz
Keywords: ANSIBLE,AUTODOC,MOD,DOCUMENTATION,FORK
Platform: UNKNOWN
Classifier: Development Status :: 4 - Beta
Classifier: Intended Audience :: Developers
Classifier: Topic :: Software Development :: Build Tools
Classifier: License :: OSI Approved :: MIT License
Classifier: Programming Language :: Python :: 3
Classifier: Programming Language :: Python :: 3.4
Classifier: Programming Language :: Python :: 3.5
Classifier: Programming Language :: Python :: 3.6
Classifier: Programming Language :: Python :: 3.7
Classifier: Programming Language :: Python :: 3.8
Classifier: Programming Language :: Python :: 3.9
